cern_sso/__init__.py
cern_sso/client.py
cern_sso/cookies.py
cern_sso/exceptions.py
cern_sso/models.py
cern_sso/tokens.py
cern_sso_python-0.4.0.dist-info/METADATA
cern_sso_python-0.4.0.dist-info/WHEEL
cern_sso_python-0.4.0.dist-info/licenses/LICENSE
cern_sso_python-0.4.0.dist-info/RECORD
