Metadata-Version: 2.4
Name: cern-sso-python
Version: 0.4.0
Summary: Python wrapper for cern-sso-cli - CERN SSO authentication
Project-URL: Homepage, https://github.com/clelange/cern-sso-python
Project-URL: Repository, https://github.com/clelange/cern-sso-python
Project-URL: Issues, https://github.com/clelange/cern-sso-python/issues
Author: Clemens Lange
License-Expression: GPL-3.0-or-later
License-File: LICENSE
Keywords: authentication,cern,kerberos,oauth,sso
Classifier: Development Status :: 3 - Alpha
Classifier: Intended Audience :: Developers
Classifier: Intended Audience :: Science/Research
Classifier: License :: OSI Approved :: GNU General Public License v3 or later (GPLv3+)
Classifier: Operating System :: OS Independent
Classifier: Programming Language :: Python :: 3
Classifier: Programming Language :: Python :: 3.9
Classifier: Programming Language :: Python :: 3.10
Classifier: Programming Language :: Python :: 3.11
Classifier: Programming Language :: Python :: 3.12
Classifier: Topic :: Scientific/Engineering
Classifier: Topic :: System :: Systems Administration :: Authentication/Directory
Requires-Python: >=3.9
Provides-Extra: dev
Requires-Dist: pytest-cov>=4.0; extra == 'dev'
Requires-Dist: pytest>=7.0; extra == 'dev'
Requires-Dist: requests; extra == 'dev'
Requires-Dist: ruff>=0.1.0; extra == 'dev'
